setup.py
pyOpenBSD/__init__.py
pyOpenBSD/_ftp_html.py
pyOpenBSD/_mirrors.py
pyOpenBSD.egg-info/PKG-INFO
pyOpenBSD.egg-info/SOURCES.txt
pyOpenBSD.egg-info/dependency_links.txt
pyOpenBSD.egg-info/top_level.txt