Metadata-Version: 1.1
Name: pyOpenBSD
Version: 0.1.1
Summary: Utilities to extract information from OpenBSD.org
Home-page: https://github.com/germfue/pyOpenBSD.git
Author: Germán Fuentes Capella
Author-email: pyOpenBSD@gfc.33mail.com
License: BSD
Keywords: openbsd website scraper
Platform: UNKNOWN
Classifier: Development Status :: 4 - Beta
Classifier: Topic :: System :: Systems Administration
Classifier: License :: OSI Approved :: BSD License
Classifier: Environment :: Console
